pharmpy/__init__.py
pharmpy/atc.py
pharmpy/druginter.py
pharmpy/epc.py
pharmpy/rxcui.py
pharmpy/utils.py
pharmpy/data/__init__.py
pharmpy/data/package.txt
pharmpy/data/product.txt
pharmpy-0.0.2.dist-info/LICENSE.txt
pharmpy-0.0.2.dist-info/METADATA
pharmpy-0.0.2.dist-info/WHEEL
pharmpy-0.0.2.dist-info/top_level.txt
pharmpy-0.0.2.dist-info/RECORD
