Metadata-Version: 2.1
Name: pharmpy
Version: 0.0.2
Summary: pharmpy is an umbrella library for searching the FDA NDC directory, Established Pharmacologic Class (EPC), Anatomical Therapeutic Chemical (ATC) through RxNav, and some other APIs on RxNav.
Home-page: https://github.com/yubin-park/pharmpy
Author: Yubin Park
Author-email: yubin.park@gmail.com
License: Apaceh 2.0
Platform: UNKNOWN
Classifier: Programming Language :: Python :: 3
Classifier: License :: OSI Approved :: Apache Software License
Classifier: Operating System :: OS Independent
